CHANGES.rst
LICENSE
MANIFEST.in
README.rst
VERSION
requirements.txt
setup.cfg
setup.py
springboard_iogt/__init__.py
springboard_iogt/application.py
springboard_iogt/config.py
springboard_iogt/events.py
springboard_iogt/filters.py
springboard_iogt/utils.py
springboard_iogt/views.py
springboard_iogt.egg-info/PKG-INFO
springboard_iogt.egg-info/SOURCES.txt
springboard_iogt.egg-info/dependency_links.txt
springboard_iogt.egg-info/entry_points.txt
springboard_iogt.egg-info/not-zip-safe
springboard_iogt.egg-info/requires.txt
springboard_iogt.egg-info/top_level.txt
springboard_iogt/locale/messages.pot
springboard_iogt/locale/ara_AE/LC_MESSAGES/messages.mo
springboard_iogt/locale/ara_AE/LC_MESSAGES/messages.po
springboard_iogt/locale/bur_MM/LC_MESSAGES/messages.mo
springboard_iogt/locale/bur_MM/LC_MESSAGES/messages.po
springboard_iogt/locale/ckb_IQ/LC_MESSAGES/messages.mo
springboard_iogt/locale/ckb_IQ/LC_MESSAGES/messages.po
springboard_iogt/locale/eng_GB/LC_MESSAGES/messages.mo
springboard_iogt/locale/eng_GB/LC_MESSAGES/messages.po
springboard_iogt/locale/fre_FR/LC_MESSAGES/messages.mo
springboard_iogt/locale/fre_FR/LC_MESSAGES/messages.po
springboard_iogt/locale/kir_KG/LC_MESSAGES/messages.mo
springboard_iogt/locale/kir_KG/LC_MESSAGES/messages.po
springboard_iogt/locale/lug_UG/LC_MESSAGES/messages.mo
springboard_iogt/locale/lug_UG/LC_MESSAGES/messages.po
springboard_iogt/locale/nep_NP/LC_MESSAGES/messages.mo
springboard_iogt/locale/nep_NP/LC_MESSAGES/messages.po
springboard_iogt/locale/por_BR/LC_MESSAGES/messages.mo
springboard_iogt/locale/por_BR/LC_MESSAGES/messages.po
springboard_iogt/locale/por_PT/LC_MESSAGES/messages.mo
springboard_iogt/locale/por_PT/LC_MESSAGES/messages.po
springboard_iogt/locale/rus_RU/LC_MESSAGES/messages.mo
springboard_iogt/locale/rus_RU/LC_MESSAGES/messages.po
springboard_iogt/locale/spa_ES/LC_MESSAGES/messages.mo
springboard_iogt/locale/spa_ES/LC_MESSAGES/messages.po
springboard_iogt/locale/swa_TZ/LC_MESSAGES/messages.mo
springboard_iogt/locale/swa_TZ/LC_MESSAGES/messages.po
springboard_iogt/static/css/README
springboard_iogt/static/css/style.css
springboard_iogt/static/css/super.css
springboard_iogt/static/css/img/arrow_darkgreen.png
springboard_iogt/static/css/img/arrow_darkgreen_flipped.png
